nyt_scraper/__init__.py
nyt_scraper/src/__init__.py
nyt_scraper/src/entities.py
nyt_scraper/src/exceptions.py
nyt_scraper/src/helpers.py
nyt_scraper/src/scraper.py
nyt_scraper/src/Scraper/__init__.py
nyt_scraper/src/Scraper/download.py
nyt_scraper/src/Scraper/scraper.py
nyt_scraper/src/Scraper/parser/__init__.py
nyt_scraper/src/Scraper/parser/attributes.py
nyt_scraper/src/Scraper/parser/general.py
nyt_scraper/src/Scraper/parser/load_data.py
nyt_scraper/src/Scraper/parser/process_initialState.py
nyt_scraper/src/Scraper/parser/typename.py
nyt_scraper-1.0.3.dist-info/LICENSE
nyt_scraper-1.0.3.dist-info/METADATA
nyt_scraper-1.0.3.dist-info/WHEEL
nyt_scraper-1.0.3.dist-info/top_level.txt
nyt_scraper-1.0.3.dist-info/RECORD
