Metadata-Version: 2.1
Name: nyt-scraper
Version: 1.0.3
Summary: A scraping library for extracting data from the New York Times
Home-page: https://github.com/Diego-Arrechea/nytimes_scraper
Author: Diego Arrechea
Author-email: diego.arrechea.job@gmail.com
License: MIT
License-File: LICENSE
Requires-Dist: beautifulsoup4 (==4.11.2)
Requires-Dist: requests
Requires-Dist: m3u8 (==3.5.0)
Requires-Dist: Pillow (==10.0.0)
